.gitignore
CHANGES.txt
MANIFEST.in
README.txt
setup.py
dateable/__init__.py
dateable.chronos.egg-info/PKG-INFO
dateable.chronos.egg-info/SOURCES.txt
dateable.chronos.egg-info/dependency_links.txt
dateable.chronos.egg-info/entry_points.txt
dateable.chronos.egg-info/namespace_packages.txt
dateable.chronos.egg-info/not-zip-safe
dateable.chronos.egg-info/requires.txt
dateable.chronos.egg-info/top_level.txt
dateable/chronos/__init__.py
dateable/chronos/config.py
dateable/chronos/configure.zcml
dateable/chronos/interfaces.py
dateable/chronos/isoweek.py
dateable/chronos/profiles.zcml
dateable/chronos/tool.gif
dateable/chronos/tool.py
dateable/chronos/utils.py
dateable/chronos/browser/__init__.py
dateable/chronos/browser/base_view.py
dateable/chronos/browser/chronos_macros.pt
dateable/chronos/browser/chronos_macros.py
dateable/chronos/browser/chronos_popup.pt
dateable/chronos/browser/chronos_popup.py
dateable/chronos/browser/config.py
dateable/chronos/browser/configure.zcml
dateable/chronos/browser/day.pt
dateable/chronos/browser/day.py
dateable/chronos/browser/displays.py
dateable/chronos/browser/displaytable.py
dateable/chronos/browser/dtutils.py
dateable/chronos/browser/eventdisplay.py
dateable/chronos/browser/events.pt
dateable/chronos/browser/events.py
dateable/chronos/browser/interfaces.py
dateable/chronos/browser/month.pt
dateable/chronos/browser/month.py
dateable/chronos/browser/overrides.zcml
dateable/chronos/browser/styles.py
dateable/chronos/browser/thumbnail.pt
dateable/chronos/browser/thumbnail.py
dateable/chronos/browser/week.pt
dateable/chronos/browser/week.py
dateable/chronos/browser/weekyear.pt
dateable/chronos/browser/resources/calendar_icon.gif
dateable/chronos/browser/resources/chronos.css
dateable/chronos/browser/resources/event-icon.gif
dateable/chronos/browser/resources/icon_import_ical.png
dateable/chronos/browser/resources/icon_subscribe_ical.gif
dateable/chronos/locales/chronos.pot
dateable/chronos/locales/custom.pot
dateable/chronos/locales/cs/LC_MESSAGES/chronos.po
dateable/chronos/locales/da/LC_MESSAGES/chronos.po
dateable/chronos/locales/de/LC_MESSAGES/chronos.po
dateable/chronos/locales/en/LC_MESSAGES/chronos.po
dateable/chronos/locales/es/LC_MESSAGES/chronos.po
dateable/chronos/locales/fr/LC_MESSAGES/chronos.po
dateable/chronos/locales/it/LC_MESSAGES/chronos.po
