Metadata-Version: 1.1
Name: dateable.chronos
Version: 1.0
Summary: Dateable calendaring views
Home-page: http://plone.org/products/dateable
Author: Lennart Regebro
Author-email: regebro@gmail.com
License: GPL
Keywords: Dateable Calendaring calendar event icalendar
Platform: UNKNOWN
Classifier: Framework :: Plone
Classifier: Programming Language :: Python
Classifier: Programming Language :: Python :: 2.6
Classifier: Programming Language :: Python :: 2.7
Classifier: License :: OSI Approved :: GNU General Public License (GPL)
Classifier: Topic :: Software Development :: Libraries :: Python Modules
